run_sample.py
WTForms_ParsleyJS-2.0.1.dist-info/DESCRIPTION.rst
WTForms_ParsleyJS-2.0.1.dist-info/METADATA
WTForms_ParsleyJS-2.0.1.dist-info/RECORD
WTForms_ParsleyJS-2.0.1.dist-info/WHEEL
WTForms_ParsleyJS-2.0.1.dist-info/metadata.json
WTForms_ParsleyJS-2.0.1.dist-info/pbr.json
WTForms_ParsleyJS-2.0.1.dist-info/top_level.txt
wtformsparsleyjs/__init__.py
wtformsparsleyjs/core.py
wtformsparsleyjs/sample/__init__.py
wtformsparsleyjs/sample/sample.py
