Metadata-Version: 2.0
Name: WTForms-ParsleyJS
Version: 2.0.1
Summary: Generate client side, parsley.js validation attributes automatically from WTForms server side validators.
Home-page: https://github.com/fuhrysteve/wtforms-parsleyjs
Author: Johannes Gehrs
Author-email: jgehrs@gmail.com
License: MIT
Download-URL: https://github.com/fuhrysteve/wtforms-parsleyjs/tarball/2.0.1
Platform: any
Classifier: Development Status :: 4 - Beta
Classifier: Environment :: Web Environment
Classifier: Intended Audience :: Developers
Classifier: License :: OSI Approved :: MIT License
Classifier: Operating System :: OS Independent
Classifier: Programming Language :: Python
Classifier: Programming Language :: Python :: 2.7
Classifier: Topic :: Internet :: WWW/HTTP :: Dynamic Content
Classifier: Topic :: Software Development :: Libraries :: Python Modules
Requires-Dist: WTForms (>=1.0.5)
Requires-Dist: frozen-flask (>=0.12)
